jp_pref/__init__.py
jp_pref/_nbdev.py
jp_pref/prefecture.py
jp_pref-0.0.5.dist-info/LICENSE
jp_pref-0.0.5.dist-info/METADATA
jp_pref-0.0.5.dist-info/WHEEL
jp_pref-0.0.5.dist-info/entry_points.txt
jp_pref-0.0.5.dist-info/top_level.txt
jp_pref-0.0.5.dist-info/RECORD
