Metadata-Version: 2.1
Name: jp-pref
Version: 0.0.5
Summary: Japan prefecture names and codes
Home-page: https://github.com/vochicong/jp_pref/tree/master/
Author: Vo Chi Cong
Author-email: chicong.v@gmail.com
License: Apache Software License 2.0
Keywords: Japan,prefecture
Platform: UNKNOWN
Classifier: Development Status :: 5 - Production/Stable
Classifier: Intended Audience :: Developers
Classifier: Natural Language :: English
Classifier: Programming Language :: Python :: 3.6
Classifier: Programming Language :: Python :: 3.7
Classifier: Programming Language :: Python :: 3.8
Classifier: License :: OSI Approved :: Apache Software License
Requires-Python: >=3.6
Requires-Dist: pandas
